data/__init__.py
data/params.json
src/__init__.py
src/my_module.py
ExampleProject_11-0.1.2.dist-info/LICENSE.txt
ExampleProject_11-0.1.2.dist-info/METADATA
ExampleProject_11-0.1.2.dist-info/WHEEL
ExampleProject_11-0.1.2.dist-info/top_level.txt
ExampleProject_11-0.1.2.dist-info/RECORD
