Metadata-Version: 2.1
Name: ExampleProject_11
Version: 0.1.2
Summary: An example project for testing.
Home-page: https://github.com/dehe1011/ExampleProject
Author: Dennis Herb
Author-email: dennis.herb@uni-ulm.de
License: BSD-3-Clause
License-File: LICENSE.txt
